Workbook

Sheet Dashboard
B2: PERSONAL FINANCE HUB — EXECUTIVE FINANCIAL DASHBOARD
B3: Active Period: 2026-09 | E3: Currency: Indonesian Rupiah (IDR) | H3: Standard: 50/30/20 Budgeting Rule
B5: EXECUTIVE KPI METRICS (ACTIVE MONTH: SEPTEMBER 2026)
B6: TOTAL INFLOW (INCOME) | D6: LIVING OUTFLOW (NEEDS + WANTS) | F6: SAVINGS & INVESTMENTS | H6: NET SAVINGS RATE (SAVINGS + SURPLUS)
B7: =SUMIFS(Ledger_Clean!$I$3:$I$100,Ledger_Clean!$F$3:$F$100,"INCOME") | D7: =SUMIFS(Ledger_Clean!$I$3:$I$100,Ledger_Clean!$F$3:$F$100,"EXPENSE",Ledger_Clean!$H$3:$H$100,"<>Savings") | F7: =SUMIFS(Ledger_Clean!$I$3:$I$100,Ledger_Clean!$F$3:$F$100,"EXPENSE",Ledger_Clean!$H$3:$H$100,"Savings") | H7: =IF(B7>0,(F7+(B7-D7-F7))/B7,0)
B10: 50/30/20 BUDGET COMPLIANCE & HEALTH | G10: MULTI-ACCOUNT LIQUIDITY & RECONCILIATION
B11: Budget Bucket | C11: Actual Spent | D11: Target Budget | E11: Health Status | G11: Account / Wallet | H11: Institution Type | I11: Starting Balance | J11: Current Balance
B12: Needs (Max 50%) | C12: =SUMIFS(Ledger_Clean!$I$3:$I$100,Ledger_Clean!$F$3:$F$100,"EXPENSE",Ledger_Clean!$H$3:$H$100,"Needs") | D12: =B7*0.5 | E12: =IF(C12<=D12,"✅ OPTIMAL (<50%)","⚠️ OVERSPENT (>50%)") | G12: BCA | H12: Commercial Bank | I12: 15000000 | J12: =I12+SUMIFS(Ledger_Clean!$I$3:$I$100,Ledger_Clean!$E$3:$E$100,G12,Ledger_Clean!$F$3:$F$100,"TRANSFER")-SUMIFS(Ledger_Clean!$I$3:$I$100,Ledger_Clean!$D$3:$D$100,G12,Ledger_Clean!$F$3:$F$100,"TRANSFER")+SUMIFS(Ledger_Clean!$I$3:$I$100,Ledger_Clean!$D$3:$D$100,G12,Ledger_Clean!$F$3:$F$100,"INCOME")-SUMIFS(Ledger_Clean!$I$3:$I$100,Ledger_Clean!$D$3:$D$100,G12,Ledger_Clean!$F$3:$F$100,"EXPENSE")
B13: Wants (Max 30%) | C13: =SUMIFS(Ledger_Clean!$I$3:$I$100,Ledger_Clean!$F$3:$F$100,"EXPENSE",Ledger_Clean!$H$3:$H$100,"Wants") | D13: =B7*0.3 | E13: =IF(C13<=D13,"✅ OPTIMAL (<30%)","⚠️ OVERSPENT (>30%)") | G13: Mandiri | H13: Commercial Bank | I13: 8500000 | J13: =I13+SUMIFS(Ledger_Clean!$I$3:$I$100,Ledger_Clean!$E$3:$E$100,G13,Ledger_Clean!$F$3:$F$100,"TRANSFER")-SUMIFS(Ledger_Clean!$I$3:$I$100,Ledger_Clean!$D$3:$D$100,G13,Ledger_Clean!$F$3:$F$100,"TRANSFER")+SUMIFS(Ledger_Clean!$I$3:$I$100,Ledger_Clean!$D$3:$D$100,G13,Ledger_Clean!$F$3:$F$100,"INCOME")-SUMIFS(Ledger_Clean!$I$3:$I$100,Ledger_Clean!$D$3:$D$100,G13,Ledger_Clean!$F$3:$F$100,"EXPENSE")
B14: Savings / Invest (Min 20%) | C14: =SUMIFS(Ledger_Clean!$I$3:$I$100,Ledger_Clean!$F$3:$F$100,"EXPENSE",Ledger_Clean!$H$3:$H$100,"Savings") | D14: =B7*0.2 | E14: =IF(C14>=D14,"✅ ON TRACK (>=20%)","⚠️ UNDERFUNDED (<20%)") | G14: BRI | H14: Commercial Bank | I14: 2000000 | J14: =I14+SUMIFS(Ledger_Clean!$I$3:$I$100,Ledger_Clean!$E$3:$E$100,G14,Ledger_Clean!$F$3:$F$100,"TRANSFER")-SUMIFS(Ledger_Clean!$I$3:$I$100,Ledger_Clean!$D$3:$D$100,G14,Ledger_Clean!$F$3:$F$100,"TRANSFER")+SUMIFS(Ledger_Clean!$I$3:$I$100,Ledger_Clean!$D$3:$D$100,G14,Ledger_Clean!$F$3:$F$100,"INCOME")-SUMIFS(Ledger_Clean!$I$3:$I$100,Ledger_Clean!$D$3:$D$100,G14,Ledger_Clean!$F$3:$F$100,"EXPENSE")
B15: Total Living Outflow | C15: =SUM(C12:C14) | D15: =SUM(D12:D14) | E15: =IF(C15<=B7,"✅ HEALTHY SURPLUS","⚠️ CASHFLOW DEFICIT") | G15: BNI | H15: Commercial Bank | I15: 1000000 | J15: =I15+SUMIFS(Ledger_Clean!$I$3:$I$100,Ledger_Clean!$E$3:$E$100,G15,Ledger_Clean!$F$3:$F$100,"TRANSFER")-SUMIFS(Ledger_Clean!$I$3:$I$100,Ledger_Clean!$D$3:$D$100,G15,Ledger_Clean!$F$3:$F$100,"TRANSFER")+SUMIFS(Ledger_Clean!$I$3:$I$100,Ledger_Clean!$D$3:$D$100,G15,Ledger_Clean!$F$3:$F$100,"INCOME")-SUMIFS(Ledger_Clean!$I$3:$I$100,Ledger_Clean!$D$3:$D$100,G15,Ledger_Clean!$F$3:$F$100,"EXPENSE")
G16: Bank Jago | H16: Digital Bank | I16: 5000000 | J16: =I16+SUMIFS(Ledger_Clean!$I$3:$I$100,Ledger_Clean!$E$3:$E$100,G16,Ledger_Clean!$F$3:$F$100,"TRANSFER")-SUMIFS(Ledger_Clean!$I$3:$I$100,Ledger_Clean!$D$3:$D$100,G16,Ledger_Clean!$F$3:$F$100,"TRANSFER")+SUMIFS(Ledger_Clean!$I$3:$I$100,Ledger_Clean!$D$3:$D$100,G16,Ledger_Clean!$F$3:$F$100,"INCOME")-SUMIFS(Ledger_Clean!$I$3:$I$100,Ledger_Clean!$D$3:$D$100,G16,Ledger_Clean!$F$3:$F$100,"EXPENSE")
B17: TOP EXPENSE CATEGORIES BREAKDOWN | G17: SeaBank | H17: Digital Bank | I17: 4000000 | J17: =I17+SUMIFS(Ledger_Clean!$I$3:$I$100,Ledger_Clean!$E$3:$E$100,G17,Ledger_Clean!$F$3:$F$100,"TRANSFER")-SUMIFS(Ledger_Clean!$I$3:$I$100,Ledger_Clean!$D$3:$D$100,G17,Ledger_Clean!$F$3:$F$100,"TRANSFER")+SUMIFS(Ledger_Clean!$I$3:$I$100,Ledger_Clean!$D$3:$D$100,G17,Ledger_Clean!$F$3:$F$100,"INCOME")-SUMIFS(Ledger_Clean!$I$3:$I$100,Ledger_Clean!$D$3:$D$100,G17,Ledger_Clean!$F$3:$F$100,"EXPENSE")
B18: Category Name | C18: Bucket | D18: Actual Spent | E18: % of Total Income | G18: GoPay | H18: E-Wallet | I18: 150000 | J18: =I18+SUMIFS(Ledger_Clean!$I$3:$I$100,Ledger_Clean!$E$3:$E$100,G18,Ledger_Clean!$F$3:$F$100,"TRANSFER")-SUMIFS(Ledger_Clean!$I$3:$I$100,Ledger_Clean!$D$3:$D$100,G18,Ledger_Clean!$F$3:$F$100,"TRANSFER")+SUMIFS(Ledger_Clean!$I$3:$I$100,Ledger_Clean!$D$3:$D$100,G18,Ledger_Clean!$F$3:$F$100,"INCOME")-SUMIFS(Ledger_Clean!$I$3:$I$100,Ledger_Clean!$D$3:$D$100,G18,Ledger_Clean!$F$3:$F$100,"EXPENSE")
B19: Groceries & Food Supplies | C19: Needs | D19: =SUMIFS(Ledger_Clean!$I$3:$I$100,Ledger_Clean!$G$3:$G$100,B19,Ledger_Clean!$F$3:$F$100,"EXPENSE") | E19: =IF($B$7>0,D19/$B$7,0) | G19: OVO | H19: E-Wallet | I19: 75000 | J19: =I19+SUMIFS(Ledger_Clean!$I$3:$I$100,Ledger_Clean!$E$3:$E$100,G19,Ledger_Clean!$F$3:$F$100,"TRANSFER")-SUMIFS(Ledger_Clean!$I$3:$I$100,Ledger_Clean!$D$3:$D$100,G19,Ledger_Clean!$F$3:$F$100,"TRANSFER")+SUMIFS(Ledger_Clean!$I$3:$I$100,Ledger_Clean!$D$3:$D$100,G19,Ledger_Clean!$F$3:$F$100,"INCOME")-SUMIFS(Ledger_Clean!$I$3:$I$100,Ledger_Clean!$D$3:$D$100,G19,Ledger_Clean!$F$3:$F$100,"EXPENSE")
B20: Utilities & Bills (PLN, Water, Net) | C20: Needs | D20: =SUMIFS(Ledger_Clean!$I$3:$I$100,Ledger_Clean!$G$3:$G$100,B20,Ledger_Clean!$F$3:$F$100,"EXPENSE") | E20: =IF($B$7>0,D20/$B$7,0) | G20: DANA | H20: E-Wallet | I20: 120000 | J20: =I20+SUMIFS(Ledger_Clean!$I$3:$I$100,Ledger_Clean!$E$3:$E$100,G20,Ledger_Clean!$F$3:$F$100,"TRANSFER")-SUMIFS(Ledger_Clean!$I$3:$I$100,Ledger_Clean!$D$3:$D$100,G20,Ledger_Clean!$F$3:$F$100,"TRANSFER")+SUMIFS(Ledger_Clean!$I$3:$I$100,Ledger_Clean!$D$3:$D$100,G20,Ledger_Clean!$F$3:$F$100,"INCOME")-SUMIFS(Ledger_Clean!$I$3:$I$100,Ledger_Clean!$D$3:$D$100,G20,Ledger_Clean!$F$3:$F$100,"EXPENSE")
B21: Transportation & Commute | C21: Needs | D21: =SUMIFS(Ledger_Clean!$I$3:$I$100,Ledger_Clean!$G$3:$G$100,B21,Ledger_Clean!$F$3:$F$100,"EXPENSE") | E21: =IF($B$7>0,D21/$B$7,0) | G21: ShopeePay | H21: E-Wallet | I21: 90000 | J21: =I21+SUMIFS(Ledger_Clean!$I$3:$I$100,Ledger_Clean!$E$3:$E$100,G21,Ledger_Clean!$F$3:$F$100,"TRANSFER")-SUMIFS(Ledger_Clean!$I$3:$I$100,Ledger_Clean!$D$3:$D$100,G21,Ledger_Clean!$F$3:$F$100,"TRANSFER")+SUMIFS(Ledger_Clean!$I$3:$I$100,Ledger_Clean!$D$3:$D$100,G21,Ledger_Clean!$F$3:$F$100,"INCOME")-SUMIFS(Ledger_Clean!$I$3:$I$100,Ledger_Clean!$D$3:$D$100,G21,Ledger_Clean!$F$3:$F$100,"EXPENSE")
B22: Healthcare & Pharmacy | C22: Needs | D22: =SUMIFS(Ledger_Clean!$I$3:$I$100,Ledger_Clean!$G$3:$G$100,B22,Ledger_Clean!$F$3:$F$100,"EXPENSE") | E22: =IF($B$7>0,D22/$B$7,0) | G22: Cash | H22: Physical Cash | I22: 500000 | J22: =I22+SUMIFS(Ledger_Clean!$I$3:$I$100,Ledger_Clean!$E$3:$E$100,G22,Ledger_Clean!$F$3:$F$100,"TRANSFER")-SUMIFS(Ledger_Clean!$I$3:$I$100,Ledger_Clean!$D$3:$D$100,G22,Ledger_Clean!$F$3:$F$100,"TRANSFER")+SUMIFS(Ledger_Clean!$I$3:$I$100,Ledger_Clean!$D$3:$D$100,G22,Ledger_Clean!$F$3:$F$100,"INCOME")-SUMIFS(Ledger_Clean!$I$3:$I$100,Ledger_Clean!$D$3:$D$100,G22,Ledger_Clean!$F$3:$F$100,"EXPENSE")
B23: Dining Out & Cafes | C23: Wants | D23: =SUMIFS(Ledger_Clean!$I$3:$I$100,Ledger_Clean!$G$3:$G$100,B23,Ledger_Clean!$F$3:$F$100,"EXPENSE") | E23: =IF($B$7>0,D23/$B$7,0) | G23: TOTAL LIQUID NET WORTH (ALL ACCOUNTS) | J23: =SUM(J12:J22)
B24: Entertainment & Subscriptions | C24: Wants | D24: =SUMIFS(Ledger_Clean!$I$3:$I$100,Ledger_Clean!$G$3:$G$100,B24,Ledger_Clean!$F$3:$F$100,"EXPENSE") | E24: =IF($B$7>0,D24/$B$7,0)
B25: Shopping & Retail | C25: Wants | D25: =SUMIFS(Ledger_Clean!$I$3:$I$100,Ledger_Clean!$G$3:$G$100,B25,Ledger_Clean!$F$3:$F$100,"EXPENSE") | E25: =IF($B$7>0,D25/$B$7,0)
B26: Mutual Funds & Stocks | C26: Savings | D26: =SUMIFS(Ledger_Clean!$I$3:$I$100,Ledger_Clean!$G$3:$G$100,B26,Ledger_Clean!$F$3:$F$100,"EXPENSE") | E26: =IF($B$7>0,D26/$B$7,0)
B27: Emergency Fund Reserve | C27: Savings | D27: =SUMIFS(Ledger_Clean!$I$3:$I$100,Ledger_Clean!$G$3:$G$100,B27,Ledger_Clean!$F$3:$F$100,"EXPENSE") | E27: =IF($B$7>0,D27/$B$7,0)

Sheet Transactions_Raw
A1: TRANSACTIONS_RAW — BRONZE INGESTION LOG (IMMUTABLE AUDIT TRAIL)
A2: raw_id | B2: ingestion_timestamp | C2: source_institution | D2: channel | E2: raw_payload | F2: parsed_amount | G2: parsed_direction | H2: payload_hash | I2: processing_status | J2: clean_ledger_ref
A3: RAW-20260901-001 | B3: 2026-09-01 07:14:00 | C3: BCA | D3: PUSH_NOTIFICATION | E3: m-Transfer: 01/09 07:14 TRSF DARI PT TECH NUSANTARA Rp 25.000.000,00 KE REK 5310294821 | F3: 25000000 | G3: CR | H3: 80286869b1f5de034e0ad569abd7d0a92d353c7b64e1280292a9369f8095a73a | I3: PROCESSED | J3: TX-202609-001
A4: RAW-20260901-002 | B4: 2026-09-01 10:30:15 | C4: BCA | D4: PUSH_NOTIFICATION | E4: m-Transfer: 01/09 10:30 TOPUP KE GOPAY RIFQI Rp 1.000.000,00 REK 5310294821 | F4: 1000000 | G4: DB | H4: a6e786371d9e041ec6ab7ffaf8654559283963f3a663359609c4aff96bc75fa7 | I4: PROCESSED | J4: TX-202609-002
A5: RAW-20260902-003 | B5: 2026-09-02 14:15:30 | C5: Mandiri | D5: SMS_NOTIFICATION | E5: Livin' Mandiri: 02/09 14:15 PEMBAYARAN PLN PASCA IDPEL 53210984 Rp 850.000,00 SUKSES | F5: 850000 | G5: DB | H5: 5bff84725c764f6d9078c704e2073621f710e73edf35dea9f4e8b753df1eadd6 | I5: PROCESSED | J5: TX-202609-003
A6: RAW-20260902-004 | B6: 2026-09-02 19:20:05 | C6: BCA | D6: EMAIL_RECEIPT | E6: BCA Autodebet: 02/09 19:20 TAGIHAN INTERNET INDIHOME NO 12249821 Rp 450.000,00 BERHASIL | F6: 450000 | G6: DB | H6: ae51507398e5ef84199e5801ab9409637e93ccbaf60847c85ffac843a3efcdce | I6: PROCESSED | J6: TX-202609-004
A7: RAW-20260903-005 | B7: 2026-09-03 16:45:10 | C7: BCA | D7: PUSH_NOTIFICATION | E7: Debit BCA: 03/09 16:45 EDC INDOMARET FRESH TB SIMATUPANG Rp 1.450.000,00 SUKSES | F7: 1450000 | G7: DB | H7: 6342db45f7e6e560f4b6d13e68dd9a2400936f6ed6cea2428f408320b637b13e | I7: PROCESSED | J7: TX-202609-005
A8: RAW-20260904-006 | B8: 2026-09-04 09:12:44 | C8: GoPay | D8: PUSH_NOTIFICATION | E8: GoPay: 04/09 09:12 Pembayaran QRIS Kopi Kenangan Menara Astra Rp 48.000 Berhasil | F8: 48000 | G8: DB | H8: 9d0e9d9b08a23128f0b13235393da7e4130ebc2dc613d63fd2f4e064839b0120 | I8: PROCESSED | J8: TX-202609-006
A9: RAW-20260905-007 | B9: 2026-09-05 08:30:12 | C9: GoPay | D9: PUSH_NOTIFICATION | E9: GoPay: 05/09 08:30 GoCar ke Pacific Place SCBD Rp 65.000 Berhasil | F9: 65000 | G9: DB | H9: 87d396f5a500a2a97071dd2392b6f2fa9f62ce5ed970bb3d47d585f3ee22c7f2 | I9: PROCESSED | J9: TX-202609-007
A10: RAW-20260906-008 | B10: 2026-09-06 12:35:50 | C10: ShopeePay | D10: PUSH_NOTIFICATION | E10: ShopeePay: 06/09 12:35 QRIS Restoran Sederhana Padang Rp 45.000 Sukses | F10: 45000 | G10: DB | H10: 563bd820a295ae2e4f84d415ab146084285496eadd03c62d748311697d246227 | I10: PROCESSED | J10: TX-202609-008
A11: RAW-20260907-009 | B11: 2026-09-07 17:20:00 | C11: Cash | D11: MANUAL_ENTRY | E11: Struk Pembelian Tunai Apotek Kimia Farma Resep Vitamin Rp 175.000 | F11: 175000 | G11: DB | H11: 3b6c789607a5a1b7734a8e8d558e19736f49944b58315262a3ef15281a4b18cb | I11: PROCESSED | J11: TX-202609-009
A12: RAW-20260908-010 | B12: 2026-09-08 03:00:18 | C12: Bank Jago | D12: PUSH_NOTIFICATION | E12: Bank Jago: 08/09 03:00 Kantong Utama Debit Netflix Premium Rp 186.000 Berhasil | F12: 186000 | G12: DB | H12: 8c34d87d3a35c044769f626c3572c60bdc44bb4c89993bbf99d981f88f7fe203 | I12: PROCESSED | J12: TX-202609-010
A13: RAW-20260909-011 | B13: 2026-09-09 15:40:22 | C13: DANA | D13: PUSH_NOTIFICATION | E13: DANA Protection: 09/09 15:40 QRIS Indomaret Snack & Minuman Rp 54.000 Berhasil | F13: 54000 | G13: DB | H13: b529387369eae0bfe32f2105b06c3664b23d774c2adf771aa3e7152e7e2a2159 | I13: PROCESSED | J13: TX-202609-011
A14: RAW-20260910-012 | B14: 2026-09-10 11:00:00 | C14: Bank Jago | D14: PUSH_NOTIFICATION | E14: Bank Jago: 10/09 11:00 Kantong Investasi Top Up Bibit Reksadana Indeks Rp 3.000.000 Berhasil | F14: 3000000 | G14: DB | H14: bc2b8da8fbb05020a8dc84cbb8027ae68f3976b41e4d38a0ac2349799932fceb | I14: PROCESSED | J14: TX-202609-012
... A22: RAW-20260918-020 | B22: 2026-09-18 11:45:00 | C22: GoPay | D22: PUSH_NOTIFICATION | E22: GoPay: 18/09 11:45 Pembayaran QRIS Infaq Masjid Nurul Iman Rp 100.000 Berhasil | F22: 100000 | G22: DB | H22: 65f092e491defb3a00a8dd0e38493885721f93e8536547dfc19fc2581c62975d | I22: PROCESSED | J22: TX-202609-020

Sheet Categories
A1: CATEGORIES — MASTER TAXONOMY & 50/30/20 BUDGET DIMENSION
A2: category_code | B2: category_name | C2: budget_bucket | D2: icon_tag | E2: monthly_budget_idr | F2: description
A3: INC-01 | B3: Salary & Compensation | C3: Income | D3: 💼 Payroll | E3: 0 | F3: Base monthly salary, corporate payroll bonus
A4: INC-02 | B4: Freelance & Consulting | C4: Income | D4: 💻 Project | E4: 0 | F4: Secondary gig income, consulting, advisory fees
A5: INC-03 | B5: Investment Returns | C5: Income | D5: 📈 Passive | E5: 0 | F5: Stock dividends, p2p interest, crypto yield
A6: INC-04 | B6: Cashback & Gifts | C6: Income | D6: 🎁 Rebate | E6: 0 | F6: Marketplace cashback, cash prizes, gifts
A7: NED-01 | B7: Groceries & Food Supplies | C7: Needs | D7: 🛒 Groceries | E7: 3000000 | F7: Supermarket, Indomaret Fresh, food provisions
A8: NED-02 | B8: Utilities & Bills (PLN, Water, Net) | C8: Needs | D8: ⚡ Utilities | E8: 1500000 | F8: PLN electricity, PDAM, Indihome, Biznet, Telkomsel
A9: NED-03 | B9: Housing & Maintenance | C9: Needs | D9: 🏠 Housing | E9: 5000000 | F9: Apartment/kost rental, maintenance, IPL fees
A10: NED-04 | B10: Transportation & Commute | C10: Needs | D10: 🚗 Commute | E10: 1200000 | F10: Bensin Pertamax/Shell, Tol, KRL, Grab/Gojek commute
A11: NED-05 | B11: Healthcare & Pharmacy | C11: Needs | D11: 🏥 Medical | E11: 800000 | F11: BPJS, insurance, pharmacy prescriptions, vitamins
A12: NED-06 | B12: Family Support & Charity | C12: Needs | D12: 🤲 Social | E12: 1000000 | F12: Family allowances, Zakat, regular infaq
A13: WNT-01 | B13: Dining Out & Cafes | C13: Wants | D13: ☕ F&B | E13: 1500000 | F13: Coffee shops, restaurants, casual eat-outs
A14: WNT-02 | B14: Entertainment & Subscriptions | C14: Wants | D14: 🍿 Media | E14: 500000 | F14: Netflix, Spotify, YouTube, ChatGPT, games
... A22: TRF-01 | B22: Internal Account Transfer | C22: Transfer | D22: 🔄 Transfer | E22: 0 | F22: Inter-account rebalancing, wallet top up

Sheet Ledger_Clean
A1: LEDGER_CLEAN — SILVER CONFORMED DOUBLE-ENTRY TRANSACTION JOURNAL
A2: transaction_id | B2: date | C2: time | D2: source_account | E2: destination_merchant | F2: type | G2: category | H2: budget_bucket | I2: amount | J2: notes | K2: payment_method | L2: raw_ref_id | M2: status
A3: TX-202609-001 | B3: 46266 | C3: 0.30138889 | D3: BCA | E3: PT Tech Nusantara | F3: INCOME | G3: Salary & Compensation | H3: =IFERROR(INDEX(Categories!$C$3:$C$22,MATCH(G3,Categories!$B$3:$B$22,0)),"Uncategorized") | I3: 25000000 | J3: Gaji Payroll Bulanan September 2026 | K3: TRANSFER | L3: RAW-20260901-001 | M3: VERIFIED
A4: TX-202609-002 | B4: 46266 | C4: 0.43767361 | D4: BCA | E4: GoPay | F4: TRANSFER | G4: Internal Account Transfer | H4: =IFERROR(INDEX(Categories!$C$3:$C$22,MATCH(G4,Categories!$B$3:$B$22,0)),"Uncategorized") | I4: 1000000 | J4: Top up saldo operasional harian GoPay | K4: TRANSFER | L4: RAW-20260901-002 | M4: VERIFIED
A5: TX-202609-003 | B5: 46267 | C5: 0.59409722 | D5: Mandiri | E5: PLN Pascabayar | F5: EXPENSE | G5: Utilities & Bills (PLN, Water, Net) | H5: =IFERROR(INDEX(Categories!$C$3:$C$22,MATCH(G5,Categories!$B$3:$B$22,0)),"Uncategorized") | I5: 850000 | J5: Tagihan listrik rumah September 2026 | K5: TRANSFER | L5: RAW-20260902-003 | M5: VERIFIED
A6: TX-202609-004 | B6: 46267 | C6: 0.80561343 | D6: BCA | E6: Indihome Internet | F6: EXPENSE | G6: Utilities & Bills (PLN, Water, Net) | H6: =IFERROR(INDEX(Categories!$C$3:$C$22,MATCH(G6,Categories!$B$3:$B$22,0)),"Uncategorized") | I6: 450000 | J6: Tagihan internet fiber optical 50 Mbps | K6: AUTODEBET | L6: RAW-20260902-004 | M6: VERIFIED
A7: TX-202609-005 | B7: 46268 | C7: 0.69803241 | D7: BCA | E7: Indomaret Fresh TB Simatupang | F7: EXPENSE | G7: Groceries & Food Supplies | H7: =IFERROR(INDEX(Categories!$C$3:$C$22,MATCH(G7,Categories!$B$3:$B$22,0)),"Uncategorized") | I7: 1450000 | J7: Belanja mingguan bahan makanan & buah | K7: DEBIT | L7: RAW-20260903-005 | M7: VERIFIED
A8: TX-202609-006 | B8: 46269 | C8: 0.38384259 | D8: GoPay | E8: Kopi Kenangan Menara Astra | F8: EXPENSE | G8: Dining Out & Cafes | H8: =IFERROR(INDEX(Categories!$C$3:$C$22,MATCH(G8,Categories!$B$3:$B$22,0)),"Uncategorized") | I8: 48000 | J8: 2x Kopi Kenangan Mantan Large QRIS | K8: QRIS | L8: RAW-20260904-006 | M8: VERIFIED
A9: TX-202609-007 | B9: 46270 | C9: 0.35430556 | D9: GoPay | E9: Gojek Transport | F9: EXPENSE | G9: Transportation & Commute | H9: =IFERROR(INDEX(Categories!$C$3:$C$22,MATCH(G9,Categories!$B$3:$B$22,0)),"Uncategorized") | I9: 65000 | J9: GoCar transport kantor SCBD meeting | K9: E_WALLET | L9: RAW-20260905-007 | M9: VERIFIED
A10: TX-202609-008 | B10: 46271 | C10: 0.52488426 | D10: ShopeePay | E10: Restoran Sederhana Padang | F10: EXPENSE | G10: Groceries & Food Supplies | H10: =IFERROR(INDEX(Categories!$C$3:$C$22,MATCH(G10,Categories!$B$3:$B$22,0)),"Uncategorized") | I10: 45000 | J10: Makan siang rendang & perkedel QRIS | K10: QRIS | L10: RAW-20260906-008 | M10: VERIFIED
A11: TX-202609-009 | B11: 46272 | C11: 0.72222222 | D11: Cash | E11: Apotek Kimia Farma | F11: EXPENSE | G11: Healthcare & Pharmacy | H11: =IFERROR(INDEX(Categories!$C$3:$C$22,MATCH(G11,Categories!$B$3:$B$22,0)),"Uncategorized") | I11: 175000 | J11: Beli suplemen vitamin C & obat flu | K11: CASH | L11: RAW-20260907-009 | M11: VERIFIED
A12: TX-202609-010 | B12: 46273 | C12: 0.12520833 | D12: Bank Jago | E12: Netflix Premium Indonesia | F12: EXPENSE | G12: Entertainment & Subscriptions | H12: =IFERROR(INDEX(Categories!$C$3:$C$22,MATCH(G12,Categories!$B$3:$B$22,0)),"Uncategorized") | I12: 186000 | J12: Langganan bulanan 4K family plan | K12: DEBIT | L12: RAW-20260908-010 | M12: VERIFIED
A13: TX-202609-011 | B13: 46274 | C13: 0.65303241 | D13: DANA | E13: Indomaret Point | F13: EXPENSE | G13: Dining Out & Cafes | H13: =IFERROR(INDEX(Categories!$C$3:$C$22,MATCH(G13,Categories!$B$3:$B$22,0)),"Uncategorized") | I13: 54000 | J13: Beli camilan sore & minuman dingin | K13: QRIS | L13: RAW-20260909-011 | M13: VERIFIED
A14: TX-202609-012 | B14: 46275 | C14: 0.45833333 | D14: Bank Jago | E14: Bibit Reksadana | F14: EXPENSE | G14: Mutual Funds & Stocks | H14: =IFERROR(INDEX(Categories!$C$3:$C$22,MATCH(G14,Categories!$B$3:$B$22,0)),"Uncategorized") | I14: 3000000 | J14: DCA rutin reksadana indeks saham BNI-AM30 | K14: TRANSFER | L14: RAW-20260910-012 | M14: VERIFIED
... A22: TX-202609-020 | B22: 46283 | C22: 0.48958333 | D22: GoPay | E22: Masjid Nurul Iman SCBD | F22: EXPENSE | G22: Family Support & Charity | H22: =IFERROR(INDEX(Categories!$C$3:$C$22,MATCH(G22,Categories!$B$3:$B$22,0)),"Uncategorized") | I22: 100000 | J22: Sedekah subuh & infaq sholat Jumat QRIS | K22: QRIS | L22: RAW-20260918-020 | M22: VERIFIED

Sheet Monthly_Summary
A1: MONTHLY_SUMMARY — GOLD ANALYTICAL MART & 50/30/20 VARIANCE ENGINE
A2: month_period | B2: total_income | C2: needs_actual | D2: needs_target_50pct | E2: needs_variance | F2: wants_actual | G2: wants_target_30pct | H2: wants_variance | I2: savings_actual | J2: savings_target_20pct | K2: total_living_expenses | L2: net_cash_surplus | M2: savings_rate_pct | N2: compliance_status
A3: 2026-09 | B3: =SUMIFS(Ledger_Clean!$I$3:$I$100,Ledger_Clean!$F$3:$F$100,"INCOME",Ledger_Clean!$B$3:$B$100,">="&DATE(2026,9,1),Ledger_Clean!$B$3:$B$100,"<="&DATE(2026,9,30)) | C3: =SUMIFS(Ledger_Clean!$I$3:$I$100,Ledger_Clean!$F$3:$F$100,"EXPENSE",Ledger_Clean!$H$3:$H$100,"Needs",Ledger_Clean!$B$3:$B$100,">="&DATE(2026,9,1),Ledger_Clean!$B$3:$B$100,"<="&DATE(2026,9,30)) | D3: =B3*0.5 | E3: =D3-C3 | F3: =SUMIFS(Ledger_Clean!$I$3:$I$100,Ledger_Clean!$F$3:$F$100,"EXPENSE",Ledger_Clean!$H$3:$H$100,"Wants",Ledger_Clean!$B$3:$B$100,">="&DATE(2026,9,1),Ledger_Clean!$B$3:$B$100,"<="&DATE(2026,9,30)) | G3: =B3*0.3 | H3: =G3-F3 | I3: =SUMIFS(Ledger_Clean!$I$3:$I$100,Ledger_Clean!$F$3:$F$100,"EXPENSE",Ledger_Clean!$H$3:$H$100,"Savings",Ledger_Clean!$B$3:$B$100,">="&DATE(2026,9,1),Ledger_Clean!$B$3:$B$100,"<="&DATE(2026,9,30)) | J3: =B3*0.2 | K3: =C3+F3 | L3: =B3-K3-I3 | M3: =IF(B3>0,(I3+L3)/B3,0) | N3: =IF(B3=0,"PENDING DATA",IF(AND(C3<=D3,F3<=G3,(I3+L3)>=J3),"✅ BALANCED (50/30/20)",IF((I3+L3)<J3,"⚠️ LOW SAVINGS (<20%)","⚠️ OVER BUDGET")))
A4: 2026-10 | B4: =SUMIFS(Ledger_Clean!$I$3:$I$100,Ledger_Clean!$F$3:$F$100,"INCOME",Ledger_Clean!$B$3:$B$100,">="&DATE(2026,10,1),Ledger_Clean!$B$3:$B$100,"<="&DATE(2026,10,31)) | C4: =SUMIFS(Ledger_Clean!$I$3:$I$100,Ledger_Clean!$F$3:$F$100,"EXPENSE",Ledger_Clean!$H$3:$H$100,"Needs",Ledger_Clean!$B$3:$B$100,">="&DATE(2026,10,1),Ledger_Clean!$B$3:$B$100,"<="&DATE(2026,10,31)) | D4: =B4*0.5 | E4: =D4-C4 | F4: =SUMIFS(Ledger_Clean!$I$3:$I$100,Ledger_Clean!$F$3:$F$100,"EXPENSE",Ledger_Clean!$H$3:$H$100,"Wants",Ledger_Clean!$B$3:$B$100,">="&DATE(2026,10,1),Ledger_Clean!$B$3:$B$100,"<="&DATE(2026,10,31)) | G4: =B4*0.3 | H4: =G4-F4 | I4: =SUMIFS(Ledger_Clean!$I$3:$I$100,Ledger_Clean!$F$3:$F$100,"EXPENSE",Ledger_Clean!$H$3:$H$100,"Savings",Ledger_Clean!$B$3:$B$100,">="&DATE(2026,10,1),Ledger_Clean!$B$3:$B$100,"<="&DATE(2026,10,31)) | J4: =B4*0.2 | K4: =C4+F4 | L4: =B4-K4-I4 | M4: =IF(B4>0,(I4+L4)/B4,0) | N4: =IF(B4=0,"PENDING DATA",IF(AND(C4<=D4,F4<=G4,(I4+L4)>=J4),"✅ BALANCED (50/30/20)",IF((I4+L4)<J4,"⚠️ LOW SAVINGS (<20%)","⚠️ OVER BUDGET")))
A5: 2026-11 | B5: =SUMIFS(Ledger_Clean!$I$3:$I$100,Ledger_Clean!$F$3:$F$100,"INCOME",Ledger_Clean!$B$3:$B$100,">="&DATE(2026,11,1),Ledger_Clean!$B$3:$B$100,"<="&DATE(2026,11,30)) | C5: =SUMIFS(Ledger_Clean!$I$3:$I$100,Ledger_Clean!$F$3:$F$100,"EXPENSE",Ledger_Clean!$H$3:$H$100,"Needs",Ledger_Clean!$B$3:$B$100,">="&DATE(2026,11,1),Ledger_Clean!$B$3:$B$100,"<="&DATE(2026,11,30)) | D5: =B5*0.5 | E5: =D5-C5 | F5: =SUMIFS(Ledger_Clean!$I$3:$I$100,Ledger_Clean!$F$3:$F$100,"EXPENSE",Ledger_Clean!$H$3:$H$100,"Wants",Ledger_Clean!$B$3:$B$100,">="&DATE(2026,11,1),Ledger_Clean!$B$3:$B$100,"<="&DATE(2026,11,30)) | G5: =B5*0.3 | H5: =G5-F5 | I5: =SUMIFS(Ledger_Clean!$I$3:$I$100,Ledger_Clean!$F$3:$F$100,"EXPENSE",Ledger_Clean!$H$3:$H$100,"Savings",Ledger_Clean!$B$3:$B$100,">="&DATE(2026,11,1),Ledger_Clean!$B$3:$B$100,"<="&DATE(2026,11,30)) | J5: =B5*0.2 | K5: =C5+F5 | L5: =B5-K5-I5 | M5: =IF(B5>0,(I5+L5)/B5,0) | N5: =IF(B5=0,"PENDING DATA",IF(AND(C5<=D5,F5<=G5,(I5+L5)>=J5),"✅ BALANCED (50/30/20)",IF((I5+L5)<J5,"⚠️ LOW SAVINGS (<20%)","⚠️ OVER BUDGET")))
A6: 2026-12 | B6: =SUMIFS(Ledger_Clean!$I$3:$I$100,Ledger_Clean!$F$3:$F$100,"INCOME",Ledger_Clean!$B$3:$B$100,">="&DATE(2026,12,1),Ledger_Clean!$B$3:$B$100,"<="&DATE(2026,12,31)) | C6: =SUMIFS(Ledger_Clean!$I$3:$I$100,Ledger_Clean!$F$3:$F$100,"EXPENSE",Ledger_Clean!$H$3:$H$100,"Needs",Ledger_Clean!$B$3:$B$100,">="&DATE(2026,12,1),Ledger_Clean!$B$3:$B$100,"<="&DATE(2026,12,31)) | D6: =B6*0.5 | E6: =D6-C6 | F6: =SUMIFS(Ledger_Clean!$I$3:$I$100,Ledger_Clean!$F$3:$F$100,"EXPENSE",Ledger_Clean!$H$3:$H$100,"Wants",Ledger_Clean!$B$3:$B$100,">="&DATE(2026,12,1),Ledger_Clean!$B$3:$B$100,"<="&DATE(2026,12,31)) | G6: =B6*0.3 | H6: =G6-F6 | I6: =SUMIFS(Ledger_Clean!$I$3:$I$100,Ledger_Clean!$F$3:$F$100,"EXPENSE",Ledger_Clean!$H$3:$H$100,"Savings",Ledger_Clean!$B$3:$B$100,">="&DATE(2026,12,1),Ledger_Clean!$B$3:$B$100,"<="&DATE(2026,12,31)) | J6: =B6*0.2 | K6: =C6+F6 | L6: =B6-K6-I6 | M6: =IF(B6>0,(I6+L6)/B6,0) | N6: =IF(B6=0,"PENDING DATA",IF(AND(C6<=D6,F6<=G6,(I6+L6)>=J6),"✅ BALANCED (50/30/20)",IF((I6+L6)<J6,"⚠️ LOW SAVINGS (<20%)","⚠️ OVER BUDGET")))
